sli/__init__.py
sli/async_ssh.py
sli/cli.py
sli/contextManager.py
sli/decorators.py
sli/encrypt.py
sli/errors.py
sli/progressBar.py
sli/skilletLineInterface.py
sli/sli_api.py
sli/ssh.py
sli/tools.py
sli/app_skillets/panos_skillet_skeleton.skillet.yaml
sli/commands/__init__.py
sli/commands/ansible_role_from_diff.py
sli/commands/ansible_role_from_skillet.py
sli/commands/base.py
sli/commands/baseline.py
sli/commands/capture.py
sli/commands/clearContext.py
sli/commands/commit.py
sli/commands/configure.py
sli/commands/connect.py
sli/commands/content_update.py
sli/commands/createTemplate.py
sli/commands/diff.py
sli/commands/license_activate.py
sli/commands/license_deactivate.py
sli/commands/listContext.py
sli/commands/load.py
sli/commands/loadConfig.py
sli/commands/loadSet.py
sli/commands/mass_ssh.py
sli/commands/mass_ssh_from_panorama.py
sli/commands/op.py
sli/commands/preview.py
sli/commands/rest.py
sli/commands/revert.py
sli/commands/rollupSkillet.py
sli/commands/rollup_playlist.py
sli/commands/save_config.py
sli/commands/showContext.py
sli/commands/show_skillet.py
sli/commands/spreadsheet.py
sli/commands/template.py
sli/commands/update_skillet_vars.py
sli/commands/validate.py
sli/commands/workflow.py
sli-0.0.1.13.dist-info/LICENSE
sli-0.0.1.13.dist-info/METADATA
sli-0.0.1.13.dist-info/WHEEL
sli-0.0.1.13.dist-info/entry_points.txt
sli-0.0.1.13.dist-info/top_level.txt
sli-0.0.1.13.dist-info/RECORD
