Metadata-Version: 2.1
Name: sli
Version: 0.0.1.13
Summary: A tool for working with Palo Alto Networks skillets
Home-page: https://paloaltonetworks.com
Author: Andrew Mallory
Author-email: amallory@paloaltonetworks.com
License: UNKNOWN
Platform: UNKNOWN
Classifier: Programming Language :: Python :: 3
Classifier: License :: OSI Approved :: MIT License
Classifier: Operating System :: OS Independent
Requires-Python: >=3.7
License-File: LICENSE
Requires-Dist: skilletlib
Requires-Dist: panforge
Requires-Dist: click
Requires-Dist: jinja2 (==3.0.1)
Requires-Dist: pycryptodome
Requires-Dist: paramiko
Requires-Dist: requests
Requires-Dist: xlsxwriter
Requires-Dist: asyncssh
